LICENSE
MANIFEST.in
README.rst
setup.py
yawd_admin.egg-info/PKG-INFO
yawd_admin.egg-info/SOURCES.txt
yawd_admin.egg-info/dependency_links.txt
yawd_admin.egg-info/not-zip-safe
yawd_admin.egg-info/requires.txt
yawd_admin.egg-info/top_level.txt
yawdadmin/.gitignore
yawdadmin/__init__.py
yawdadmin/__init__.pyc
yawdadmin/admin.py
yawdadmin/admin.pyc
yawdadmin/admin_options.py
yawdadmin/admin_options.pyc
yawdadmin/fields.py
yawdadmin/fields.pyc
yawdadmin/forms.py
yawdadmin/forms.pyc
yawdadmin/middleware.py
yawdadmin/middleware.pyc
yawdadmin/models.py
yawdadmin/models.pyc
yawdadmin/sites.py
yawdadmin/sites.pyc
yawdadmin/tests.py
yawdadmin/tests.pyc
yawdadmin/utils.py
yawdadmin/utils.pyc
yawdadmin/views.py
yawdadmin/views.pyc
yawdadmin/widgets.py
yawdadmin/widgets.pyc
yawdadmin/conf/__init__.py
yawdadmin/conf/__init__.pyc
yawdadmin/conf/settings.py
yawdadmin/conf/settings.pyc
yawdadmin/locale/el/LC_MESSAGES/django.mo
yawdadmin/locale/el/LC_MESSAGES/django.po
yawdadmin/locale/el/LC_MESSAGES/djangojs.mo
yawdadmin/locale/el/LC_MESSAGES/djangojs.po
yawdadmin/static/admin/js/SelectFilter2.js
yawdadmin/static/admin/js/actions.js
yawdadmin/static/admin/js/actions.min.js
yawdadmin/static/admin/js/inlines.js
yawdadmin/static/admin/js/inlines.min.js
yawdadmin/static/admin/js/prepopulate.js
yawdadmin/static/admin/js/prepopulate.min.js
yawdadmin/static/admin/js/admin/DateTimeShortcuts.js
yawdadmin/static/yawd-admin/css/admin.css
yawdadmin/static/yawd-admin/css/bootstrap.css
yawdadmin/static/yawd-admin/css/bootstrap.min.css
yawdadmin/static/yawd-admin/css/font-awesome-ie7.min.css
yawdadmin/static/yawd-admin/css/fancybox/blank.gif
yawdadmin/static/yawd-admin/css/fancybox/fancybox_loading.gif
yawdadmin/static/yawd-admin/css/fancybox/fancybox_overlay.png
yawdadmin/static/yawd-admin/css/fancybox/fancybox_sprite.png
yawdadmin/static/yawd-admin/css/fancybox/jquery.fancybox.css
yawdadmin/static/yawd-admin/css/select2/LICENSE
yawdadmin/static/yawd-admin/css/select2/README.md
yawdadmin/static/yawd-admin/css/select2/component.json
yawdadmin/static/yawd-admin/css/select2/release.sh
yawdadmin/static/yawd-admin/css/select2/select2-spinner.gif
yawdadmin/static/yawd-admin/css/select2/select2.css
