Metadata-Version: 1.1
Name: yawd-admin
Version: 0.7.0
Summary: An administration website for Django
Home-page: http://yawd.eu/open-source-projects/yawd-admin/
Author: yawd
Author-email: info@yawd.eu
License: BSD
Platform: UNKNOWN
Classifier: Development Status :: 4 - Beta
Classifier: Environment :: Web Environment
Classifier: Framework :: Django
Classifier: Intended Audience :: Developers
Classifier: License :: OSI Approved :: BSD License
Classifier: Operating System :: OS Independent
Classifier: Programming Language :: Python
Classifier: Topic :: Software Development :: Libraries
